Metadata-Version: 1.0
Name: Tesla
Version: 0.2.6
Summary: Pylons template with Elixir ORM bindings
Home-page: http://tesla-pylons-elixir.googlecode.com
Author: beachcoder
Author-email: danjac_35@yahoo.co.uk
License: MIT
Keywords: sqlalchemy elixir sacontext pylons wsgi makotemplate paste
Platform: UNKNOWN
